{"extension":"RDFTransform","version":"2.2.1","baseIRI":"http://127.0.0.1:3333/","namespaces":{"rdf":"http://www.w3.org/1999/02/22-rdf-syntax-ns#","rdfs":"http://www.w3.org/2000/01/rdf-schema#","owl":"http://www.w3.org/2002/07/owl#","xsd":"http://www.w3.org/2001/XMLSchema#","vcard":"http://www.w3.org/2006/vcard/ns#"},"subjectMappings":[{"prefix":"","valueSource":{"source":"constant","constant":"MilitaryConflict"},"propertyMappings":[{"prefix":"rdfs","valueSource":{"source":"constant","constant":"subClassOf"},"objectMappings":[{"prefix":"sem","valueType":{"type":"iri"},"valueSource":{"source":"constant","constant":"Event"}}]}]},{"prefix":"","valueSource":{"source":"column","columnName":"wikititle"},"propertyMappings":[{"prefix":"","valueSource":{"source":"constant","constant":"partof"},"objectMappings":[{"valueType":{"type":"literal"},"valueSource":{"source":"column","columnName":"partof"}}]},{"prefix":"","valueSource":{"source":"constant","constant":"casus"},"objectMappings":[{"valueType":{"type":"literal"},"valueSource":{"source":"column","columnName":"casus"}}]},{"prefix":"","valueSource":{"source":"constant","constant":"teritory"},"objectMappings":[{"valueType":{"type":"literal"},"valueSource":{"source":"column","columnName":"teritory"}}]},{"prefix":"","valueSource":{"source":"constant","constant":"strength1"},"objectMappings":[{"valueType":{"type":"literal"},"valueSource":{"source":"column","columnName":"strength1"}}]},{"prefix":"","valueSource":{"source":"constant","constant":"strength2"},"objectMappings":[{"valueType":{"type":"literal"},"valueSource":{"source":"column","columnName":"strength2"}}]},{"prefix":"","valueSource":{"source":"constant","constant":"casualties1"},"objectMappings":[{"valueType":{"type":"literal"},"valueSource":{"source":"column","columnName":"casualties1"}}]},{"prefix":"","valueSource":{"source":"constant","constant":"casualties2"},"objectMappings":[{"valueType":{"type":"literal"},"valueSource":{"source":"column","columnName":"casualties2"}}]},{"prefix":"rdfs","valueSource":{"source":"constant","constant":"label"},"objectMappings":[{"valueType":{"type":"literal"},"valueSource":{"source":"column","columnName":"wikititle"}}]},{"prefix":"rdf","valueSource":{"source":"constant","constant":"type"},"objectMappings":[{"prefix":"","valueType":{"type":"iri"},"valueSource":{"source":"constant","constant":"MilitaryConflict"}}]}]}]}